NPytdl/__init__.py
NPytdl/crawler.py
NPytdl/dataParser.py
NPytdl/webBug.py
NPytdl-4.1.2.dist-info/LICENSE
NPytdl-4.1.2.dist-info/METADATA
NPytdl-4.1.2.dist-info/WHEEL
NPytdl-4.1.2.dist-info/top_level.txt
NPytdl-4.1.2.dist-info/RECORD
